spinepose/VERSION
spinepose/__init__.py
spinepose/_version.py
spinepose/inference.py
spinepose/metainfo.py
spinepose/pose_estimator.py
spinepose/pose_tracker.py
spinepose/tools/__init__.py
spinepose/tools/base_solution.py
spinepose/tools/base_tool.py
spinepose/tools/smoothing.py
spinepose/tools/visualization.py
spinepose/tools/object_detection/__init__.py
spinepose/tools/object_detection/post_processings.py
spinepose/tools/object_detection/yolox.py
spinepose/tools/pose_estimation/__init__.py
spinepose/tools/pose_estimation/post_processings.py
spinepose/tools/pose_estimation/pre_processings.py
spinepose/tools/pose_estimation/rtmpose.py
spinepose/tools/utils/__init__.py
spinepose/tools/utils/file.py
spinepose/tools/utils/multithreading.py
spinepose/tools/utils/types.py
spinepose-2.0.0.dist-info/licenses/LICENSE
spinepose-2.0.0.dist-info/METADATA
spinepose-2.0.0.dist-info/WHEEL
spinepose-2.0.0.dist-info/entry_points.txt
spinepose-2.0.0.dist-info/top_level.txt
spinepose-2.0.0.dist-info/RECORD
