Metadata-Version: 2.4
Name: spinepose
Version: 2.0.0
Summary: A Python package for 2D human spine keypoint estimation in the wild.
Home-page: https://github.com/dfki-av/spinepose
Author: Muhammad Saif Ullah Khan
Author-email: saifkhichi96@gmail.com
License: CC-BY-NC-4.0
Project-URL: Bug Tracker, https://github.com/dfki-av/spinepose/issues
Project-URL: Documentation, https://github.com/dfki-av/spinepose/tree/main?tab=readme-ov-file
Keywords: pose-estimation,spine,biomechanics,sports
Platform: any
Classifier: Development Status :: 5 - Production/Stable
Classifier: Intended Audience :: Science/Research
Classifier: Intended Audience :: Healthcare Industry
Classifier: Intended Audience :: Education
Classifier: Operating System :: OS Independent
Classifier: Programming Language :: Python :: 3
Classifier: Programming Language :: Python :: 3.9
Classifier: Programming Language :: Python :: 3.10
Classifier: Programming Language :: Python :: 3.11
Classifier: Programming Language :: Python :: 3.12
Classifier: Topic :: Scientific/Engineering
Classifier: Topic :: Scientific/Engineering :: Image Recognition
Classifier: Topic :: Scientific/Engineering :: Medical Science Apps.
Classifier: Topic :: Multimedia :: Graphics
Requires-Python: >=3.9
License-File: LICENSE
Requires-Dist: anytree
Requires-Dist: numpy
Requires-Dist: OneEuroFilter
Requires-Dist: opencv-python
Requires-Dist: onnxruntime
Requires-Dist: torch
Requires-Dist: tqdm
Provides-Extra: gpu
Requires-Dist: onnxruntime-gpu; extra == "gpu"
Dynamic: license-file
